LICENSE
README.md
setup.py
sw_django_logger.egg-info/PKG-INFO
sw_django_logger.egg-info/SOURCES.txt
sw_django_logger.egg-info/dependency_links.txt
sw_django_logger.egg-info/requires.txt
sw_django_logger.egg-info/top_level.txt
sw_logger/__init__.py
sw_logger/admin.py
sw_logger/consts.py
sw_logger/exceptions.py
sw_logger/filters.py
sw_logger/forms.py
sw_logger/handlers.py
sw_logger/models.py
sw_logger/tools.py
sw_logger/urls.py
sw_logger/views.py
sw_logger/migrations/0001_initial.py
sw_logger/migrations/0002_auto_20170624_1618.py
sw_logger/migrations/0003_auto_20170624_1913.py
sw_logger/migrations/0004_auto_20180810_1127.py
sw_logger/migrations/0005_add_indexes.py
sw_logger/migrations/__init__.py