Metadata-Version: 2.2
Name: sw-django-logger
Version: 0.0.18
Summary: Log handling and representing for django projects
Home-page: https://github.com/telminov/sw-django-logger
Author: Telminov Sergey
Author-email: sergey@telminov.ru
License: The MIT License
License-File: LICENSE
Requires-Dist: django
Requires-Dist: django-filter
Dynamic: author
Dynamic: author-email
Dynamic: home-page
Dynamic: license
Dynamic: requires-dist
Dynamic: summary
